langchain_encrypted_redis_memory/EncryptedRedisChatMemory.py
langchain_encrypted_redis_memory/__init__.py
langchain_encrypted_redis_memory-1.0.2.dist-info/licenses/LICENSE
langchain_encrypted_redis_memory-1.0.2.dist-info/METADATA
langchain_encrypted_redis_memory-1.0.2.dist-info/WHEEL
langchain_encrypted_redis_memory-1.0.2.dist-info/top_level.txt
langchain_encrypted_redis_memory-1.0.2.dist-info/RECORD
