Metadata-Version: 2.4
Name: langchain-encrypted-redis-memory
Version: 1.0.2
Summary: Encrypted Redis chat message history for LangChain with AES-128 encryption via mores-encryption.
Author-email: Hemant Kumar <hemant.kumardeveloper@gmail.com>
License: MIT License
Project-URL: Homepage, https://github.com/HATAKEkakshi/langchain-encrypted-redis-memory
Project-URL: Documentation, https://github.com/HATAKEkakshi/langchain-encrypted-redis-memory
Project-URL: Source, https://github.com/HATAKEkakshi/langchain-encrypted-redis-memory
Project-URL: Issues, https://github.com/HATAKEkakshi/langchain-encrypted-redis-memory/issues
Keywords: langchain,redis,encryption,chat-history,memory,aes,fernet,security
Classifier: Development Status :: 5 - Production/Stable
Classifier: Intended Audience :: Developers
Classifier: License :: OSI Approved :: MIT License
Classifier: Operating System :: OS Independent
Classifier: Programming Language :: Python :: 3
Classifier: Programming Language :: Python :: 3.8
Classifier: Programming Language :: Python :: 3.9
Classifier: Programming Language :: Python :: 3.10
Classifier: Programming Language :: Python :: 3.11
Classifier: Programming Language :: Python :: 3.12
Classifier: Topic :: Security :: Cryptography
Classifier: Topic :: Software Development :: Libraries :: Python Modules
Requires-Python: >=3.8
License-File: LICENSE
Requires-Dist: langchain>=0.1.0
Requires-Dist: langchain-community>=0.0.1
Requires-Dist: langchain-core>=0.1.0
Requires-Dist: redis>=4.0.0
Requires-Dist: mores-encryption>=0.1.0
Provides-Extra: dev
Requires-Dist: pytest>=7.0.0; extra == "dev"
Requires-Dist: pytest-cov>=4.0.0; extra == "dev"
Requires-Dist: flake8>=6.0.0; extra == "dev"
Requires-Dist: black>=23.0.0; extra == "dev"
Requires-Dist: mypy>=1.0.0; extra == "dev"
Dynamic: license-file
